main.py
setup.py
shaiduwkv.egg-info/PKG-INFO
shaiduwkv.egg-info/SOURCES.txt
shaiduwkv.egg-info/dependency_links.txt
shaiduwkv.egg-info/requires.txt
shaiduwkv.egg-info/top_level.txt